timefmt/__init__.py
timefmt/_auto.py
timefmt/_helpers.py
timefmt/dt.py
timefmt/td.py
timefmt-1.1.11.dist-info/LICENSE
timefmt-1.1.11.dist-info/WHEEL
timefmt-1.1.11.dist-info/METADATA
timefmt-1.1.11.dist-info/RECORD
