Metadata-Version: 2.1
Name: timefmt
Version: 1.1.11
Summary: Provides methods to manipulate and format various time-based objects into human-readable strings.
Author-email: Ella Jameson <ellagjameson@gmail.com>
Requires-Python: >=3.10
Classifier: Development Status :: 5 - Production/Stable
Classifier: License :: OSI Approved :: GNU General Public License v3 or later (GPLv3+)
Classifier: Programming Language :: Python
Classifier: Programming Language :: Python :: 3
Classifier: Programming Language :: Python :: 3.10
Classifier: Programming Language :: Python :: 3.11
Classifier: Programming Language :: Python :: 3.12
Classifier: Programming Language :: Python :: 3 :: Only
Requires-Dist: onecondition >=1.0.0
Project-URL: documentation, https://timefmt.readthedocs.io/en/latest/index.html
Project-URL: homepage, https://github.com/nimaid/python-timeformat
Project-URL: issues, https://github.com/nimaid/python-timeformat/issues
Project-URL: repository, https://github.com/nimaid/python-timeformat
